gesang_sqlalchemy/__init__.py
gesang_sqlalchemy/core.py
gesang_sqlalchemy/exc.py
gesang_sqlalchemy/model.py
gesang_sqlalchemy/transaction.py
gesang_sqlalchemy/utils.py
gesang_sqlalchemy-1.0.0.dist-info/LICENSE
gesang_sqlalchemy-1.0.0.dist-info/METADATA
gesang_sqlalchemy-1.0.0.dist-info/WHEEL
gesang_sqlalchemy-1.0.0.dist-info/top_level.txt
gesang_sqlalchemy-1.0.0.dist-info/RECORD
