Metadata-Version: 2.1
Name: gesang-sqlalchemy
Version: 1.0.0
Summary: A sql orm framework based on sqlalchemy for gesang api framework.
Home-page: UNKNOWN
Author: Dong Zhang
Author-email: 785576549@qq.com
License: UNKNOWN
Platform: any
Classifier: Development Status :: 3 - Alpha
Classifier: Programming Language :: Python :: 3.7
Requires-Dist: sqlalchemy
Requires-Dist: gesang
